idealab_empty_project/__init__.py
idealab_empty_project/empty_main_widget.py
idealab_empty_project-0.0.1.dist-info/DESCRIPTION.rst
idealab_empty_project-0.0.1.dist-info/METADATA
idealab_empty_project-0.0.1.dist-info/RECORD
idealab_empty_project-0.0.1.dist-info/WHEEL
idealab_empty_project-0.0.1.dist-info/metadata.json
idealab_empty_project-0.0.1.dist-info/top_level.txt
