Metadata-Version: 2.0
Name: idealab-empty-project
Version: 0.0.1
Summary: Empty QT Project developed by the IDEAlab.
Home-page: UNKNOWN
Author: Dan Aukes
Author-email: danaukes@danaukes.com
License: MIT
Platform: UNKNOWN
Classifier: Programming Language :: Python
Classifier: Programming Language :: Python :: 3
Requires-Dist: imageio
